malti/__init__.py
malti/sent_splitter/__init__.py
malti/sent_splitter/sent_splitter.py
malti/sent_splitter/km_sent_splitter/__init__.py
malti/sent_splitter/km_sent_splitter/km_sent_splitter.py
malti/tokeniser/__init__.py
malti/tokeniser/regex_tokeniser.py
malti/tokeniser/tokeniser.py
malti/tokeniser/km_tokeniser/__init__.py
malti/tokeniser/km_tokeniser/km_tokeniser.py
malti-0.2.0.dist-info/LICENSE
malti-0.2.0.dist-info/METADATA
malti-0.2.0.dist-info/WHEEL
malti-0.2.0.dist-info/top_level.txt
malti-0.2.0.dist-info/RECORD
