Metadata-Version: 2.1
Name: malti
Version: 0.2.0
Summary: A library for processing text in the Maltese language.
Author-email: Kurt Micallef <kurt.micallef@um.edu.mt>, Marc Tanti <marc.tanti@um.edu.mt>
License: MIT License
Project-URL: Repository, https://github.com/MLRS/malti/
Project-URL: Documentation, https://malti.readthedocs.io/
Keywords: Malti,Maltese
Classifier: Development Status :: 4 - Beta
Classifier: License :: OSI Approved :: MIT License
Classifier: Natural Language :: English
Classifier: Programming Language :: Python :: 3
Classifier: Typing :: Typed
Classifier: Topic :: Software Development :: Libraries
Classifier: Topic :: Text Processing :: Linguistic
Requires-Python: >=3.9
License-File: LICENSE
Requires-Dist: sentence-splitter==1.4
